README.md
setup.py
termwidth.py
termwidth.egg-info/PKG-INFO
termwidth.egg-info/SOURCES.txt
termwidth.egg-info/dependency_links.txt
termwidth.egg-info/not-zip-safe
termwidth.egg-info/top_level.txt