Metadata-Version: 2.1
Name: termwidth
Version: 2019.1125.2909
Summary: Terminal width detection library
Home-page: http://github.com/ArneBachmann/termwidth
Author: Arne Bachmann
Author-email: ArneBachmann@users.noreply.github.com
Maintainer: Arne Bachmann
Maintainer-email: ArneBachmann@users.noreply.github.com
License: GNU General Public License v3 (GPLv3)
Keywords: termsize terminal width height size posix curses tput linux windows
Platform: UNKNOWN
Classifier: Development Status :: 5 - Production/Stable
Classifier: Intended Audience :: Developers
Classifier: License :: OSI Approved :: GNU General Public License v3 (GPLv3)
Classifier: Operating System :: OS Independent
Classifier: Programming Language :: Python
Classifier: Programming Language :: Python :: 3
Classifier: Programming Language :: Python :: 3 :: Only
